MANIFEST.in
README.md
README.rst
setup.py
convoy/__init__.py
convoy/middleware.py
convoy/models.py
convoy/stores.py
convoy/tests.py
convoy/utils.py
convoy/templatetags/__init__.py
convoy/templatetags/convoytags.py
django_asset_convoy.egg-info/PKG-INFO
django_asset_convoy.egg-info/SOURCES.txt
django_asset_convoy.egg-info/dependency_links.txt
django_asset_convoy.egg-info/requires.txt
django_asset_convoy.egg-info/top_level.txt