Metadata-Version: 1.0
Name: django-asset-convoy
Version: 0.1.3
Summary: Asset packager for Django applications
Home-page: UNKNOWN
Author: Ted Tieken <ted.tieken@gmail.com>, Peter Conerly <pconerly@gmail.com>
Author-email: ted.tieken@gmail.com
License: MIT
Platform: UNKNOWN
